protean/__init__.py
protean/api_client.py
protean/api_response.py
protean/configuration.py
protean/exceptions.py
protean/protean_api_client.py
protean/rest.py
protean/api/__init__.py
protean/api/chat_api.py
protean/api/data_api.py
protean/api/dataset_api.py
protean/api/user_api.py
protean/models/__init__.py
protean/models/breakpoint_strategy.py
protean/models/chat_question_request.py
protean/models/chat_question_response.py
protean/models/chunk.py
protean/models/client_tool_call.py
protean/models/client_tool_definition.py
protean/models/client_tools.py
protean/models/combining_strategy.py
protean/models/create_dataset_request.py
protean/models/create_documents_in_dataset_request.py
protean/models/create_documents_in_datasource_request.py
protean/models/create_fixed_size_chunks_request.py
protean/models/create_fixed_size_chunks_response.py
protean/models/create_semantic_chunks_request.py
protean/models/create_semantic_chunks_response.py
protean/models/dataset_search_request.py
protean/models/dataset_search_response.py
protean/models/dataset_search_type.py
protean/models/exception_response.py
protean/models/get_datasets_response.py
protean/models/internal_error.py
protean/models/not_authenticated.py
protean/models/not_authorized.py
protean/models/not_found.py
protean/models/not_found_cause.py
protean/models/not_found_cause_stack_trace_inner.py
protean/models/protean_dataset.py
protean/models/protean_datasource.py
protean/models/protean_document.py
protean/models/question500_response.py
protean/models/sentence.py
protean/models/similarity_strategy.py
protean/models/text_splitting_strategy.py
protean/models/update_dataset_request.py
protean/models/update_documents_request.py
protean/models/user.py
protean/models/validation_failed.py
cogrow_protean-0.0.4.dist-info/METADATA
cogrow_protean-0.0.4.dist-info/WHEEL
cogrow_protean-0.0.4.dist-info/top_level.txt
cogrow_protean-0.0.4.dist-info/RECORD
