Metadata-Version: 2.4
Name: cogrow-protean
Version: 0.0.4
Summary: The official Python library for the Protean API
Author-email: CoGrow <support@cogrow.tech>
License-Expression: MIT
Classifier: Development Status :: 3 - Alpha
Classifier: Intended Audience :: Developers
Classifier: Operating System :: OS Independent
Classifier: Topic :: Software Development :: Libraries :: Python Modules
Requires-Python: >=3.11
Requires-Dist: urllib3<3.0.0,>=2.1.0
Requires-Dist: python_dateutil>=2.8.2
Requires-Dist: pydantic>=2
Requires-Dist: typing-extensions>=4.7.1
